pypkgs_jg/__init__.py
pypkgs_jg/pypkgs_jg.py
pypkgs_jg-0.1.0.dist-info/LICENSE
pypkgs_jg-0.1.0.dist-info/WHEEL
pypkgs_jg-0.1.0.dist-info/METADATA
pypkgs_jg-0.1.0.dist-info/RECORD
