Metadata-Version: 2.1
Name: pypkgs-jg
Version: 0.1.0
Summary: Packaging dummy assignment
License: "MIT"
Author: Jayme Gordon
Author-email: jaymegordo@gmail.com
Requires-Python: >=3.8,<4.0
Classifier: License :: Other/Proprietary License
Classifier: Programming Language :: Python :: 3
Classifier: Programming Language :: Python :: 3.8
Classifier: Programming Language :: Python :: 3.9
Requires-Dist: pandas (>=1.2.2,<2.0.0)
